astrago/__init__.py
astrago/dataSender.py
astrago/tracking.py
astrago/val.py
astrago/integration/__init__.py
astrago/integration/keras.py
astrago/integration/pytorchLightning.py
astrago/resource/__init__.py
astrago/resource/resourceCollector.py
astrago/resource/resourceDTO.py
astrago-0.0.9.dist-info/METADATA
astrago-0.0.9.dist-info/WHEEL
astrago-0.0.9.dist-info/top_level.txt
astrago-0.0.9.dist-info/RECORD
